AUTHORS
LICENSE
MANIFEST.in
README.rst
setup.cfg
setup.py
Djinja.egg-info/PKG-INFO
Djinja.egg-info/SOURCES.txt
Djinja.egg-info/dependency_links.txt
Djinja.egg-info/not-zip-safe
Djinja.egg-info/requires.txt
Djinja.egg-info/top_level.txt
djinja/__init__.py
djinja/contrib/__init__.py
djinja/contrib/admin/__init__.py
djinja/contrib/admin/templates/.DS_Store
djinja/contrib/admin/templates/._.DS_Store
djinja/contrib/admin/templates/admin/._404.html
djinja/contrib/admin/templates/admin/._500.html
djinja/contrib/admin/templates/admin/._actions.html
djinja/contrib/admin/templates/admin/._app_index.html
djinja/contrib/admin/templates/admin/._base.html
djinja/contrib/admin/templates/admin/._base_site.html
djinja/contrib/admin/templates/admin/._change_form.html
djinja/contrib/admin/templates/admin/._change_list.html
djinja/contrib/admin/templates/admin/._change_list_results.html
djinja/contrib/admin/templates/admin/._date_hierarchy.html
djinja/contrib/admin/templates/admin/._delete_confirmation.html
djinja/contrib/admin/templates/admin/._delete_selected_confirmation.html
djinja/contrib/admin/templates/admin/._filter.html
djinja/contrib/admin/templates/admin/._index.html
djinja/contrib/admin/templates/admin/._invalid_setup.html
djinja/contrib/admin/templates/admin/._login.html
djinja/contrib/admin/templates/admin/._object_history.html
djinja/contrib/admin/templates/admin/._pagination.html
djinja/contrib/admin/templates/admin/._prepopulated_fields_js.html
djinja/contrib/admin/templates/admin/._search_form.html
djinja/contrib/admin/templates/admin/._submit_line.html
djinja/contrib/admin/templates/admin/404.html
djinja/contrib/admin/templates/admin/500.html
djinja/contrib/admin/templates/admin/actions.html
djinja/contrib/admin/templates/admin/app_index.html
djinja/contrib/admin/templates/admin/base.html
djinja/contrib/admin/templates/admin/base_site.html
djinja/contrib/admin/templates/admin/change_form.html
djinja/contrib/admin/templates/admin/change_list.html
djinja/contrib/admin/templates/admin/change_list_results.html
djinja/contrib/admin/templates/admin/date_hierarchy.html
djinja/contrib/admin/templates/admin/delete_confirmation.html
