Metadata-Version: 1.0
Name: Djinja
Version: 0.6
Summary: A package that makes possible the integration of Jinja2 in Django, in a clean way.
Home-page: http://github.com/syrusakbary/djinja
Author: Syrus Akbary Nieto
Author-email: me@syrusakbary.com
License: BSD
Platform: UNKNOWN
Classifier: Framework :: Django
Classifier: Intended Audience :: Developers
Classifier: Intended Audience :: System Administrators
Classifier: Operating System :: OS Independent
Classifier: Intended Audience :: Developers
Classifier: License :: OSI Approved :: BSD License
Classifier: Operating System :: OS Independent
Classifier: Programming Language :: Python
Classifier: Topic :: Software Development :: Libraries :: Python Modules
